[
  {
    "keyword": "ai video generator",
    "search_volume": 27000,
    "cpc": 2.67,
    "competition": 0.74
  },
  {
    "keyword": "text to video ai",
    "search_volume": 19500,
    "cpc": 2.34,
    "competition": 0.71
  },
  {
    "keyword": "ai video creator",
    "search_volume": 14300,
    "cpc": 2.45,
    "competition": 0.72
  },
  {
    "keyword": "ai video editing",
    "search_volume": 11200,
    "cpc": 2.89,
    "competition": 0.75
  },
  {
    "keyword": "video generation ai",
    "search_volume": 8700,
    "cpc": 2.78,
    "competition": 0.73
  },
  {
    "keyword": "ai animation generator",
    "search_volume": 6400,
    "cpc": 2.56,
    "competition": 0.7
  },
  {
    "keyword": "ai video maker",
    "search_volume": 4900,
    "cpc": 2.12,
    "competition": 0.69
  },
  {
    "keyword": "automated video creation",
    "search_volume": 3600,
    "cpc": 3.12,
    "competition": 0.76
  },
  {
    "keyword": "ai video marketing",
    "search_volume": 2500,
    "cpc": 3.45,
    "competition": 0.78
  },
  {
    "keyword": "ai avatar video",
    "search_volume": 1800,
    "cpc": 2.23,
    "competition": 0.68
  }
]