{
  "category": "Code Generation", 
  "description": "AI-powered coding assistants and code generation tools for developers to write, debug, and optimize code faster with intelligent suggestions.",
  "tools": [
    {
      "id": "cursor",
      "name": "Cursor",
      "slug": "cursor",
      "logo": "/images/tools/cursor-logo.svg",
      "meta": {
        "title": "Cursor Review, Pricing, Features & Alternatives [2025]",
        "description": "AI-first code editor with advanced tab completion and context-aware chat. Built on VS Code with whole codebase understanding and predictive editing.",
        "keywords": "cursor, cursor ai, cursor review, cursor pricing, ai code editor, vs code alternative, github copilot alternative, 2025",
        "canonical": "https://siteoptz.ai/tools/cursor",
        "openGraph": {
          "title": "Cursor - AI-First Code Editor",
          "description": "Advanced AI code editor with whole codebase context and predictive editing",
          "type": "article",
          "url": "https://siteoptz.ai/tools/cursor",
          "image": "https://siteoptz.ai/images/tools/cursor-logo.svg",
          "site_name": "SiteOptz"
        },
        "twitter": {
          "card": "summary_large_image",
          "title": "Cursor - AI Code Editor",
          "description": "Advanced AI code editor with whole codebase context and predictive editing",
          "image": "https://siteoptz.ai/images/tools/cursor-logo.svg"
        }
      },
      "schema": {
        "@type": "Product",
        "@context": "https://schema.org",
        "name": "Cursor",
        "description": "AI-first code editor with advanced tab completion and context-aware chat",
        "image": "https://siteoptz.ai/images/tools/cursor-logo.svg",
        "url": "https://siteoptz.ai/tools/cursor",
        "brand": {
          "@type": "Brand",
          "name": "Anysphere"
        },
        "category": null,
        "aggregateRating": {
          "@type": "AggregateRating",
          "ratingValue": 4.7,
          "reviewCount": 4200,
          "bestRating": 5,
          "worstRating": 1
        },
        "offers": {
          "@type": "Offer",
          "price": 20,
          "priceCurrency": "USD",
          "availability": "https://schema.org/InStock",
          "url": "https://cursor.sh",
          "description": "Free tier available, Pro at $20/month"
        }
      },
      "overview": {
        "developer": "Anysphere",
        "release_year": 2023,
        "category": "Code Generation",
        "description": "Cursor is an AI-first code editor built on VS Code with advanced AI capabilities including whole codebase understanding, predictive editing, and context-aware chat assistance.",
        "website": "https://cursor.sh",
        "support": "Discord Community, Documentation, Email Support",
        "use_cases": [
          "Full-stack development",
          "Code refactoring and optimization",
          "Bug detection and fixing",
          "Documentation generation",
          "Code review assistance",
          "Learning new codebases"
        ],
        "integrations": [
          "VS Code extensions",
          "Git integration",
          "Terminal integration",
          "Multiple AI models",
          "Language servers",
          "Debugging tools"
        ]
      },
      "features": [
        "AI-powered tab completion",
        "Context-aware chat",
        "Whole codebase understanding",
        "Predictive editing",
        "Multi-line suggestions",
        "Code explanation",
        "Refactoring assistance"
      ],
      "pros": [
        "Superior file-level awareness vs competitors",
        "Advanced refactoring capabilities",
        "Excellent context understanding",
        "Fast and responsive interface",
        "Built on familiar VS Code foundation",
        "Multiple AI model support"
      ],
      "cons": [
        "Higher pricing than GitHub Copilot",
        "Requires internet connection",
        "Limited free tier usage",
        "Still in active development"
      ],
      "pricing": [
        {
          "plan": "Free",
          "price_per_month": 0,
          "features": [
            "2,000 completions/month",
            "50 slow premium requests",
            "Basic features",
            "Community support"
          ]
        },
        {
          "plan": "Pro",
          "price_per_month": 20,
          "features": [
            "Unlimited completions",
            "500 fast premium requests",
            "Advanced features",
            "Priority support"
          ]
        },
        {
          "plan": "Business",
          "price_per_month": 40,
          "features": [
            "Everything in Pro",
            "Team management",
            "Usage analytics",
            "Priority support"
          ]
        }
      ],
      "benchmarks": {
        "speed": 9,
        "accuracy": 9,
        "integration": 8,
        "ease_of_use": 8,
        "value": 7
      },
      "related_tools": [
        "github-copilot",
        "codeium",
        "tabnine"
      ],
      "affiliate_link": "https://cursor.sh",
      "search_volume": 4200,
      "cpc": 4.5,
      "use_cases": [
        "AI-Powered Development",
        "Code Refactoring",
        "Bug Detection",
        "Documentation Generation",
        "Code Review"
      ],
      "tags": [
        "ai code editor",
        "vs code",
        "predictive editing"
      ]
    },
    {
      "id": "windsurf",
      "name": "Windsurf",
      "slug": "windsurf", 
      "logo": "/images/tools/windsurf-logo.svg",
      "meta": {
        "title": "Windsurf Review, Pricing, Features & Alternatives [2025]",
        "description": "First agentic IDE with Cascade technology for deep contextual awareness. AI coding partner that automates routine tasks and maintains project context.",
        "keywords": "windsurf, windsurf ide, codeium windsurf, agentic ide, cascade technology, ai coding assistant, 2025",
        "canonical": "https://siteoptz.ai/tools/windsurf",
        "openGraph": {
          "title": "Windsurf - First Agentic IDE",
          "description": "AI coding partner with Cascade technology for contextual awareness",
          "type": "article",
          "url": "https://siteoptz.ai/tools/windsurf",
          "image": "https://siteoptz.ai/images/tools/windsurf-logo.svg",
          "site_name": "SiteOptz"
        },
        "twitter": {
          "card": "summary_large_image",
          "title": "Windsurf - Agentic IDE",
          "description": "AI coding partner with Cascade technology for contextual awareness",
          "image": "https://siteoptz.ai/images/tools/windsurf-logo.svg"
        }
      },
      "schema": {
        "@type": "Product",
        "@context": "https://schema.org",
        "name": "Windsurf",
        "description": "First agentic IDE with Cascade technology for deep contextual awareness",
        "image": "https://siteoptz.ai/images/tools/windsurf-logo.svg",
        "url": "https://siteoptz.ai/tools/windsurf",
        "brand": {
          "@type": "Brand",
          "name": "Codeium"
        },
        "category": null,
        "aggregateRating": {
          "@type": "AggregateRating",
          "ratingValue": 4.6,
          "reviewCount": 2100,
          "bestRating": 5,
          "worstRating": 1
        },
        "offers": {
          "@type": "Offer",
          "price": 15,
          "priceCurrency": "USD",
          "availability": "https://schema.org/InStock",
          "url": "https://codeium.com/windsurf",
          "description": "Free tier available, Pro at $15/month"
        }
      },
      "overview": {
        "developer": "Codeium",
        "release_year": 2024,
        "category": "Code Generation",
        "description": "Windsurf is the first agentic IDE that combines deep contextual awareness through Cascade technology with chat-based AI interaction, making AI feel like a true coding partner.",
        "website": "https://codeium.com/windsurf",
        "support": "Discord Community, Documentation, Support Team",
        "use_cases": [
          "Agentic coding assistance",
          "Automated routine tasks",
          "Contextual code generation",
          "Project-wide refactoring",
          "Intelligent debugging",
          "Code documentation"
        ],
        "integrations": [
          "Git version control",
          "Multiple language support",
          "Extension marketplace",
          "Terminal integration",
          "Debugging tools",
          "Testing frameworks"
        ]
      },
      "features": [
        "Cascade contextual awareness",
        "Chat-based agentic experience",
        "Automated task execution",
        "Deep project understanding",
        "Intelligent code suggestions",
        "Multi-file editing",
        "Context-aware debugging"
      ],
      "pros": [
        "Generous free tier offering",
        "Intuitive chat-based interface",
        "Advanced contextual awareness",
        "Feels like coding partner vs tool",
        "Competitive pricing at $15/month",
        "Active development and updates"
      ],
      "cons": [
        "Newer platform with less ecosystem",
        "Limited third-party extensions",
        "Learning curve for agentic approach",
        "Requires internet connectivity"
      ],
      "pricing": [
        {
          "plan": "Free",
          "price_per_month": 0,
          "features": [
            "Unlimited autocomplete",
            "Chat functionality",
            "Basic Cascade features",
            "Community support"
          ]
        },
        {
          "plan": "Pro",
          "price_per_month": 15,
          "features": [
            "Advanced Cascade features",
            "Priority model access",
            "Enhanced chat capabilities",
            "Premium support"
          ]
        }
      ],
      "benchmarks": {
        "speed": 8,
        "accuracy": 8,
        "integration": 7,
        "ease_of_use": 9,
        "value": 9
      },
      "related_tools": [
        "cursor",
        "github-copilot",
        "codeium"
      ],
      "affiliate_link": "https://codeium.com/windsurf",
      "search_volume": 2100,
      "cpc": 3.8,
      "use_cases": [
        "Agentic Development",
        "Automated Coding Tasks",
        "Contextual Assistance",
        "Project Refactoring",
        "Intelligent Debugging"
      ],
      "tags": [
        "agentic ide",
        "cascade technology",
        "chat-based coding"
      ]
    }
  ]
}